tests/__init__.py
tests/test_easy_query.py
tests/test_gridded.py
tests/test_model.py
tests/test_regional.py
tests/test_tdmethods.py
tethys/__init__.py
tethys/model.py
tethys/datareader/__init__.py
tethys/datareader/easy_query.py
tethys/datareader/gridded.py
tethys/datareader/maps.py
tethys/datareader/point.py
tethys/datareader/regional.py
tethys/tdmethods/__init__.py
tethys/tdmethods/domestic.py
tethys/tdmethods/electricity.py
tethys/tdmethods/irrigation.py
tethys/utils/__init__.py
tethys/utils/install_supplement.py
tethys/utils/region_to_id_mapping.py
tethys/utils/spatial.py
tethys_downscaling-2.1.dist-info/LICENSE
tethys_downscaling-2.1.dist-info/METADATA
tethys_downscaling-2.1.dist-info/WHEEL
tethys_downscaling-2.1.dist-info/top_level.txt
tethys_downscaling-2.1.dist-info/RECORD
